wanip/__init__.py
wanip/providers.py
wanip/wanip.py
wanip-2025.7.26.0.dist-info/METADATA
wanip-2025.7.26.0.dist-info/WHEEL
wanip-2025.7.26.0.dist-info/entry_points.txt
wanip-2025.7.26.0.dist-info/top_level.txt
wanip-2025.7.26.0.dist-info/RECORD
