Metadata-Version: 2.4
Name: wanip
Version: 2025.7.26.0
Summary: Determine your WAN IP
Author-email: Ann T Ropea <bedhanger@gmx.de>
License-Expression: MIT
Project-URL: Homepage, https://gitlab.com/bedhanger/mwe/-/tree/master/python/wanip
Requires-Dist: lsattr
